wiegand.py
micropython_wiegand-1.1.0.dist-info/DESCRIPTION.rst
micropython_wiegand-1.1.0.dist-info/METADATA
micropython_wiegand-1.1.0.dist-info/RECORD
micropython_wiegand-1.1.0.dist-info/WHEEL
micropython_wiegand-1.1.0.dist-info/metadata.json
micropython_wiegand-1.1.0.dist-info/top_level.txt
