Metadata-Version: 2.0
Name: micropython-wiegand
Version: 1.1.0
Summary: MicroPython class to read from a Wiegand card reader
Home-page: https://github.com/pjz/micropython-wiegand
Author: Paul Jimenez
Author-email: pj@place.org
License: LGPLv3+
Keywords: micropython wiegand keycard
Platform: UNKNOWN
Classifier: Development Status :: 4 - Beta
Classifier: Intended Audience :: Developers
Classifier: Topic :: Software Development :: Libraries
Classifier: Topic :: System :: Hardware
Classifier: License :: OSI Approved :: GNU Lesser General Public License v3 or later (LGPLv3+)
Classifier: Programming Language :: Python :: 3
Classifier: Programming Language :: Python :: 3.4
Classifier: Programming Language :: Python :: 3.5
